atomworks/__init__.py
atomworks/biotite_patch.py
atomworks/common.py
atomworks/constants.py
atomworks/enums.py
atomworks/py.typed
atomworks/io/__init__.py
atomworks/io/parser.py
atomworks/io/template.py
atomworks/io/tools/chembl_transformations.smirks
atomworks/io/tools/fasta.py
atomworks/io/tools/inference.py
atomworks/io/tools/rdkit.py
atomworks/io/transforms/atom_array.py
atomworks/io/transforms/categories.py
atomworks/io/utils/__init__.py
atomworks/io/utils/assembly.py
atomworks/io/utils/atom_array.py
atomworks/io/utils/atom_array_plus.py
atomworks/io/utils/bonds.py
atomworks/io/utils/ccd.py
atomworks/io/utils/chain.py
atomworks/io/utils/compression.py
atomworks/io/utils/error.py
atomworks/io/utils/io_utils.py
atomworks/io/utils/non_rcsb.py
atomworks/io/utils/query.py
atomworks/io/utils/scatter.py
atomworks/io/utils/selection.py
atomworks/io/utils/sequence.py
atomworks/io/utils/testing.py
atomworks/io/utils/visualize.py
atomworks/ml/__init__.py
atomworks/ml/encoding_definitions.py
atomworks/ml/example_id.py
atomworks/ml/samplers.py
atomworks/ml/conditions/__init__.py
atomworks/ml/conditions/annotator.py
atomworks/ml/conditions/base.py
atomworks/ml/conditions/conditions.py
atomworks/ml/datasets/README.md
atomworks/ml/datasets/__init__.py
atomworks/ml/datasets/base.py
atomworks/ml/datasets/concat_dataset.py
atomworks/ml/datasets/file_dataset.py
atomworks/ml/datasets/pandas_dataset.py
atomworks/ml/datasets/loaders/__init__.py
atomworks/ml/datasets/loaders/base.py
atomworks/ml/datasets/loaders/cif.py
atomworks/ml/datasets/parsers/__init__.py
atomworks/ml/datasets/parsers/base.py
atomworks/ml/datasets/parsers/custom_metadata_row_parsers.py
atomworks/ml/datasets/parsers/default_metadata_row_parsers.py
atomworks/ml/executables/__init__.py
atomworks/ml/executables/hbplus.py
atomworks/ml/executables/hhfilter.py
atomworks/ml/executables/mmseqs2.py
atomworks/ml/executables/x3dna.py
atomworks/ml/pipelines/__init__.py
atomworks/ml/pipelines/af3.py
atomworks-2.2.0.dist-info/METADATA
atomworks-2.2.0.dist-info/WHEEL
atomworks-2.2.0.dist-info/entry_points.txt
atomworks-2.2.0.dist-info/licenses/LICENSE.md
atomworks-2.2.0.dist-info/RECORD
