Metadata-Version: 2.4
Name: atomworks
Version: 2.2.0
Summary: A research-oriented data toolkit for training biomolecular deep-learning foundation models
Project-URL: homepage, https://rosettacommons.github.io/atomworks/latest/index.html
Project-URL: repository, https://github.com/RosettaCommons/atomworks
Project-URL: documentation, https://rosettacommons.github.io/atomworks/latest/index.html
Author-email: Institute for Protein Design <contact@ipd.uw.edu>
License: BSD 3-Clause License
License-File: LICENSE.md
Classifier: Intended Audience :: Developers
Classifier: Intended Audience :: Science/Research
Classifier: License :: OSI Approved :: BSD License
Classifier: Natural Language :: English
Classifier: Operating System :: MacOS
Classifier: Operating System :: Microsoft :: Windows
Classifier: Operating System :: POSIX :: Linux
Classifier: Programming Language :: Python :: 3
Classifier: Programming Language :: Python :: Implementation :: CPython
Classifier: Topic :: Scientific/Engineering :: Bio-Informatics
Requires-Python: >=3.11
Requires-Dist: biotite==1.4.0
Requires-Dist: cython<4,>=3.0.0
Requires-Dist: cytoolz<1,>=0.12.3
Requires-Dist: hydride<2,>=1.2.3
Requires-Dist: numpy<3,>=1.25.0
Requires-Dist: pandas<2.4,>=2.2
Requires-Dist: py3dmol<3,>=2.2.1
Requires-Dist: pyarrow==17.0.0
Requires-Dist: pymol-remote>=0.0.5
Requires-Dist: rdkit<2025.9,>=2024.3.5
Requires-Dist: scipy<2,>=1.13.1
Requires-Dist: tqdm<5,>=4.65.0
Requires-Dist: typer<1,>=0.12.5
Requires-Dist: zstandard<1,>=0.21.0
Provides-Extra: ase
Requires-Dist: ase-db-backends<1,>=0.10.0; extra == 'ase'
Requires-Dist: ase<4,>=3.22.0; extra == 'ase'
Requires-Dist: lmdb<2,>=1.5.0; extra == 'ase'
Provides-Extra: dev
Requires-Dist: ipykernel>=6.28.0; extra == 'dev'
Requires-Dist: pytest-benchmark<6,>=5.0.0; extra == 'dev'
Requires-Dist: pytest-cov<5,>=4.1.0; extra == 'dev'
Requires-Dist: pytest-dotenv<1,>=0.5.2; extra == 'dev'
Requires-Dist: pytest-testmon<3,>=2.1.1; extra == 'dev'
Requires-Dist: pytest-xdist<4,>=3.6.1; extra == 'dev'
Requires-Dist: pytest<9,>=8.2.0; extra == 'dev'
Requires-Dist: ruff==0.8.3; extra == 'dev'
Provides-Extra: docs
Requires-Dist: matplotlib<4,>=3.10.0; extra == 'docs'
Requires-Dist: pydata-sphinx-theme<1,>=0.16.1; extra == 'docs'
Requires-Dist: sphinx-gallery<1,>=0.19.0; extra == 'docs'
Requires-Dist: sphinx<9,>=8.0.0; extra == 'docs'
Provides-Extra: ml
Requires-Dist: beartype<1,>=0.18.0; extra == 'ml'
Requires-Dist: einops<1,>=0.7.0; extra == 'ml'
Requires-Dist: jaxtyping<1,>=0.2.17; extra == 'ml'
Requires-Dist: torch<2.8,>=2.2.0; extra == 'ml'
Provides-Extra: openbabel
Requires-Dist: openbabel-wheel==3.1.1.22; extra == 'openbabel'
